dc_input/__init__.py
dc_input/_get_input.py
dc_input/_log.py
dc_input/_types.py
dc_input/_version.py
dc_input/_pipeline/__init__.py
dc_input/_pipeline/_parse_input.py
dc_input/_pipeline/_utils.py
dc_input/_pipeline/build_session_graph.py
dc_input/_pipeline/initialize_schema.py
dc_input/_pipeline/normalize_schema.py
dc_input/_pipeline/prepare_parsers.py
dc_input/_pipeline/run_user_session.py
dc_input/_pipeline/validate_user_definitions.py
dc_input-0.2.5.dist-info/METADATA
dc_input-0.2.5.dist-info/WHEEL
dc_input-0.2.5.dist-info/licenses/LICENSE
dc_input-0.2.5.dist-info/RECORD
