Metadata-Version: 2.4
Name: dc-input
Version: 0.2.5
Summary: Interactively fill dataclass instances via the command line.
Project-URL: Homepage, https://github.com/jdvanwijk/dc-input
Project-URL: Repository, https://github.com/jdvanwijk/dc-input
Author-email: Jan Ebel van Wijk <jan86@posteo.de>
License: MIT
License-File: LICENSE
Keywords: cli,dataclass,input,interactive,wizard
Classifier: License :: OSI Approved :: MIT License
Classifier: Operating System :: OS Independent
Classifier: Programming Language :: Python :: 3
Requires-Python: >=3.10
